{
  "oczy_k": {
    "title": "Oczy — kobieta",
    "causes": [
      "Przykładowa przyczyna 1",
      "Przykładowa przyczyna 2"
    ],
    "symptoms": [
      "Przykładowy objaw 1",
      "Przykładowy objaw 2"
    ],
    "concerns": [
      "⚠️ Obawy/pilne sygnały np. nagła utrata wzroku",
      "⚠️ Silny ból oka"
    ],
    "doctors": [
      "Okulista",
      "POZ"
    ],
    "medications": [
      "Sztuczne łzy",
      "Krople antyhistaminowe"
    ],
    "first_aid": [
      "Płukanie oczu solą fizjologiczną",
      "Unikanie alergenów"
    ],
    "emergency": [
      "Nagła utrata wzroku — natychmiast 112",
      "Silny ból oka po urazie — SOR"
    ],
    "description": "Tu możesz dodać dodatkowy opis np. o profilaktyce, diecie, stylu życia."
  },

  "serce_m": {
    "title": "Serce — mężczyzna",
    "causes": [
      "Choroba wieńcowa",
      "Zawał"
    ],
    "symptoms": [
      "Ból w klatce piersiowej",
      "Duszność"
    ],
    "concerns": [
      "⚠️ Ból w klatce z promieniowaniem do ręki — wezwij 112",
      "⚠️ Nagłe zimne poty i osłabienie"
    ],
    "doctors": [
      "Kardiolog",
      "Lekarz rodzinny"
    ],
    "medications": [
      "Nitrogliceryna",
      "Beta-blokery"
    ],
    "first_aid": [
      "Pozycja siedząca z oparciem",
      "Wezwanie pomocy"
    ],
    "emergency": [
      "Silny, uciskający ból w klatce + duszność — 112",
      "Utrata przytomności — 112"
    ],
    "description": "Tu dodatkowe informacje o chorobach serca i stylu życia."
  }
